{"Create": ["Act", "Arrange", "Assemble", "Combine", "Compose", "Construct", "Create", "Design", "Develop", "Devise", "Formulate", "Generate", "Improve", "Infer", "Invent", "Imagine", "Plan", "Predict", "Prepare", "Revise", "Show", "Write"], "Evaluate": ["Argue", "Assess", "Choose", "Compare", "Conclude", "Criticize","Criticise","Debate", "Decide", "Defend", "Determine", "Evaluate", "Justify", "Prioritize","Prioritise", "Rate", "Recommend", "Support", "Value", "Critique", "Review", "Judge"], "Analyse": ["Calculate", "Categorize","Categorise","Classify", "Compare", "Contrast", "Diagram", "Differentiate", "Discover", "Distinguish", "Examine", "Experiment", "Group", "Interpret", "Investigate", "Order", "Organize", "Question", "Relate", "Research", "Sequence", "Solve", "Survey", "Integrate", "Analyse", "Organise", "Deconstruct"], "Apply": ["Adapt", "Apply", "Calculate", "Change", "Compute", "Demonstrate", "Dramatize","Dramatise", "Draw", "Experiment", "Illustrate", "List", "Make", "Manipulate", "Practice", "Produce", "Sequence", "Show", "Solve", "Teach", "Use", "Interpret"], "Understand": ["Ask", "Calculate", "Convert", "Describe", "Discuss", "Explain", "Identify", "Locate", "Observe", "Recognize", "Report", "Research", "Retell", "Review", "Summarize","Summarise", "Tell", "Compare", "Understand", "Illustrate"], "Remember": ["Choose", "Cite", "Define", "Describe", "Group", "Know", "Label", "List", "Listen", "Locate", "Match", "Memorize","Memorise", "Name", "Quote", "Recall", "Recite", "Record", "Repeat", "Select", "Underline", "Recognise", "Identify", "Retrieve"]}